setup.py
src/main.py
src/random_security_test_pkg.egg-info/PKG-INFO
src/random_security_test_pkg.egg-info/SOURCES.txt
src/random_security_test_pkg.egg-info/dependency_links.txt
src/random_security_test_pkg.egg-info/top_level.txt