Metadata-Version: 2.1
Name: random-security-test-pkg
Version: 1.1.0
Summary: 112
Author: Benny123
Author-email: my@company.com
License: LGPL 3.0
